cpufreq/__init__.py
cpufreq/cpufreq.py
cpufreq/run.py
cpufreq-0.3.5.dist-info/LICENSE.txt
cpufreq-0.3.5.dist-info/METADATA
cpufreq-0.3.5.dist-info/WHEEL
cpufreq-0.3.5.dist-info/entry_points.txt
cpufreq-0.3.5.dist-info/top_level.txt
cpufreq-0.3.5.dist-info/RECORD
