Metadata-Version: 2.1
Name: cpufreq
Version: 0.3.5
Summary: CPU Frequency manage tool
Home-page: https://github.com/VitorRamos/cpufreq
Author: Vitor Ramos, Alex Furtunato
Author-email: ramos.vitor89@gmail.com, alex.furtunato@academico.ifrn.edu.br
License: MIT
Keywords: cpufreq tool
Platform: UNKNOWN
Classifier: Development Status :: 3 - Alpha
Classifier: Topic :: Software Development :: Build Tools
Classifier: Topic :: Software Development :: Libraries :: Python Modules
Classifier: Topic :: Scientific/Engineering
Classifier: License :: OSI Approved :: MIT License
Classifier: Programming Language :: Python :: 3
